rk_mcprotocol/__init__.py
rk_mcprotocol/main.py
rk_mcprotocal-0.0.2.dist-info/METADATA
rk_mcprotocal-0.0.2.dist-info/WHEEL
rk_mcprotocal-0.0.2.dist-info/top_level.txt
rk_mcprotocal-0.0.2.dist-info/RECORD
