Metadata-Version: 2.1
Name: rk_mcprotocal
Version: 0.0.2
